whintpy/__init__.py
whintpy/config/__init__.py
whintpy/config/settings.py
whintpy/config/typesdealer.py
whintpy/config/typesmapping.py
whintpy/connection/__init__.py
whintpy/connection/authentication.py
whintpy/connection/base_authentication.py
whintpy/connection/connection.py
whintpy/connection/jwt_authetication.py
whintpy/connection/ldap_authentication.py
whintpy/deposit/__init__.py
whintpy/deposit/docsfilters.py
whintpy/deposit/document.py
whintpy/deposit/document_utils.py
whintpy/deposit/documents_manager.py
whintpy/filters/__init__.py
whintpy/filters/basecompare.py
whintpy/filters/basefilters.py
whintpy/filters/datecompare.py
whintpy/filters/filteredset.py
whintpy/filters/numcompare.py
whintpy/filters/strcompare.py
WhintPy-1.1.dist-info/AUTHORS.md
WhintPy-1.1.dist-info/LICENSE
WhintPy-1.1.dist-info/METADATA
WhintPy-1.1.dist-info/WHEEL
WhintPy-1.1.dist-info/top_level.txt
WhintPy-1.1.dist-info/RECORD
