Metadata-Version: 2.1
Name: WhintPy
Version: 1.1
Summary: WhintPy is a pure Python-based solution to manage documents with or without authentication access.
Author-email: Brigitte Bigi <contact@sppas.org>
License: GNU AFFERO GENERAL PUBLIC LICENSE
Project-URL: Documentation, https://whintpy.sourceforge.io/
Project-URL: Homepage, https://sourceforge.net/projects/whintpy/
Keywords: python,web,html,documents,files,filters,search,deposit,connection,authentication
Classifier: Programming Language :: Python
Classifier: License :: OSI Approved :: GNU Affero General Public License v3 or later (AGPLv3+)
Classifier: Operating System :: OS Independent
Classifier: Development Status :: 5 - Production/Stable
Requires-Python: >=3.9
License-File: LICENSE
License-File: AUTHORS.md
Requires-Dist: WhakerPy>=0.6
Requires-Dist: ldap3
Requires-Dist: PyJWT
Provides-Extra: docs
Requires-Dist: pygments; extra == "docs"
Requires-Dist: markdown2; extra == "docs"
Requires-Dist: ClammingPy>=1.8; extra == "docs"
Provides-Extra: tests
Requires-Dist: coverage~=7.3.0; extra == "tests"
Requires-Dist: python-dotenv~=1.0.0; extra == "tests"
